{
  "independent_personal_pronouns":
    {"separate":
        {
          "sg": {"1":"’enā",
                 "2":{"m":"’at",
                      "f":"’at"},
                 "3":{"m":"hu",
                      "f":"hi"}
                },
          "pl": {"1":"ḥnan",
                 "2":{"m":"’atton",
                      "f":"’attēn"},
                 "3":{"m":"hennon",
                      "f":"hennēn"}
                }
        },
      "enclitic":
        {
          "sg": {"1":"nā",
                 "2":{"m":"t",
                      "f":"t"},
                 "3":{"m":["w", "u"],
                      "f":["y", "i"]}
                },
          "pl": {"1":"nan",
                 "2":{"m":"tton",
                      "f":"ttēn"},
                 "3":{"m":"’ennon",
                      "f":"’ennēn"}
                }
        }
    },
  "suffixed_personal_pronouns":
    {
      "after_consonants": {
        "sg": {
          "1": "y",
          "2": {
            "m": ["āḵ", "ḵ"],
            "f": ["ēḵ", "ḵ"]
          },
          "3": {
            "m": ["ēh", "y"],
            "f": ["āh", "h"]
          }
        },
        "pl": {
          "1": ["an", "n"],
          "2": {
            "m": "ḵon",
            "f": "ḵen"
          },
          "3": {
            "m": "hon",
            "f": "hēn"
          }
        }
      }
    }
}